Robotframework_iRODS-0.0.4.dist-info/DESCRIPTION.rst
Robotframework_iRODS-0.0.4.dist-info/METADATA
Robotframework_iRODS-0.0.4.dist-info/RECORD
Robotframework_iRODS-0.0.4.dist-info/WHEEL
Robotframework_iRODS-0.0.4.dist-info/dependency_links.txt
Robotframework_iRODS-0.0.4.dist-info/metadata.json
Robotframework_iRODS-0.0.4.dist-info/top_level.txt
iRODSLibrary/__init__.py
iRODSLibrary/iRODSLibrary.py
iRODSLibrary/version.py
