Metadata-Version: 2.0
Name: Robotframework-iRODS
Version: 0.0.4
Summary: Robot Framework keyword library wrapper around python-irodsclient
Home-page: https://github.com/cyverse/Robotframework-iRODS-Library
Author: Andre Mercer
Author-email: amercer@cyverse.org
License: University of Arizona License
Platform: UNKNOWN
Classifier: Development Status :: 5 - Production/Stable
Classifier: License :: Public Domain
Classifier: Operating System :: OS Independent
Classifier: Programming Language :: Python
Classifier: Topic :: Software Development :: Testing
Requires-Dist: python-irodsclient
Requires-Dist: robotframework
